src/__init__.py
src/pytra.py
src/utils/__init__.py
src/utils/constants.py
src/utils/decorators.py
src/utils/googletrans_helpers.py
src/utils/translator.py
pytra-0.3.dist-info/LICENSE
pytra-0.3.dist-info/METADATA
pytra-0.3.dist-info/WHEEL
pytra-0.3.dist-info/entry_points.txt
pytra-0.3.dist-info/top_level.txt
pytra-0.3.dist-info/RECORD
