Metadata-Version: 2.1
Name: pytra
Version: 0.3
Summary: Simple command-line tool for translating
Home-page: https://github.com/GeorgeStambulyants/pytra
Author: George Stambulyants
Author-email: george.stamb16@gmail.com
License: MIT
Platform: UNKNOWN
Classifier: License :: OSI Approved :: MIT License
Classifier: Programming Language :: Python :: 3
Classifier: Programming Language :: Python :: 3.7
Requires-Python: >=3.7
Requires-Dist: click
Requires-Dist: googletrans
